kartskrape/__init__.py
kartskrape/dataset_downloader.py
kartskrape/datasets.py
kartskrape/html.py
kartskrape/kartverket_api.py
kartskrape/selection.py
kartskrape/config/__init__.py
kartskrape/config/datasets.yaml
kartskrape/config/datasets2.yaml
kartskrape/config/urls.py
kartskrape/models/__init__.py
kartskrape/models/dataset.py
kartskrape/models/receipt.py
kartskrape/utils/__init__.py
kartskrape/utils/generate_config.py
kartskrape/utils/log.py
kartskrape-1.4.0.dist-info/DESCRIPTION.rst
kartskrape-1.4.0.dist-info/METADATA
kartskrape-1.4.0.dist-info/RECORD
kartskrape-1.4.0.dist-info/WHEEL
kartskrape-1.4.0.dist-info/metadata.json
kartskrape-1.4.0.dist-info/top_level.txt
